djcms_blog/__init__.py
djcms_blog/admin.py
djcms_blog/models.py
djcms_blog/settings.py
djcms_blog/sitemaps.py
djcms_blog/tests.py
djcms_blog/urls.py
djcms_blog/utils.py
djcms_blog/views.py
djcms_blog/locale/en/LC_MESSAGES/django.mo
djcms_blog/locale/en/LC_MESSAGES/django.po
djcms_blog/locale/es/LC_MESSAGES/django.mo
djcms_blog/locale/es/LC_MESSAGES/django.po
djcms_blog/migrations/0001_initial.py
djcms_blog/migrations/0002_auto_20190120_2013.py
djcms_blog/migrations/0003_auto_20190121_1712.py
djcms_blog/migrations/0004_auto_20190125_2000.py
djcms_blog/migrations/0005_auto_20190125_2230.py
djcms_blog/migrations/0006_auto_20190303_1447.py
djcms_blog/migrations/__init__.py
djcms_blog/static/djcms_blog/css/djcms_blog.css
djcms_blog/static/djcms_blog/css/semantic.css
djcms_blog/static/djcms_blog/css/semantic.min.css
djcms_blog/static/djcms_blog/css/themes/default/assets/fonts/brand-icons.eot
djcms_blog/static/djcms_blog/css/themes/default/assets/fonts/brand-icons.svg
djcms_blog/static/djcms_blog/css/themes/default/assets/fonts/brand-icons.ttf
djcms_blog/static/djcms_blog/css/themes/default/assets/fonts/brand-icons.woff
djcms_blog/static/djcms_blog/css/themes/default/assets/fonts/brand-icons.woff2
djcms_blog/static/djcms_blog/css/themes/default/assets/fonts/icons.eot
djcms_blog/static/djcms_blog/css/themes/default/assets/fonts/icons.otf
djcms_blog/static/djcms_blog/css/themes/default/assets/fonts/icons.svg
djcms_blog/static/djcms_blog/css/themes/default/assets/fonts/icons.ttf
djcms_blog/static/djcms_blog/css/themes/default/assets/fonts/icons.woff
djcms_blog/static/djcms_blog/css/themes/default/assets/fonts/icons.woff2
djcms_blog/static/djcms_blog/css/themes/default/assets/fonts/outline-icons.eot
djcms_blog/static/djcms_blog/css/themes/default/assets/fonts/outline-icons.svg
djcms_blog/static/djcms_blog/css/themes/default/assets/fonts/outline-icons.ttf
djcms_blog/static/djcms_blog/css/themes/default/assets/fonts/outline-icons.woff
djcms_blog-0.2.4.dist-info/AUTHORS.rst
djcms_blog-0.2.4.dist-info/LICENSE
djcms_blog-0.2.4.dist-info/METADATA
djcms_blog-0.2.4.dist-info/WHEEL
djcms_blog-0.2.4.dist-info/top_level.txt
djcms_blog-0.2.4.dist-info/RECORD
