Metadata-Version: 2.1
Name: djcms-blog
Version: 0.2.4
Summary: Simple Django Blog app using Markdown
Home-page: https://github.com/carlosmart626/djcms_blog
Author: Carlos Martinez
Author-email: me@carlosmart.co
License: MIT license
Keywords: djcms_blog
Platform: UNKNOWN
Classifier: Development Status :: 2 - Pre-Alpha
Classifier: Intended Audience :: Developers
Classifier: License :: OSI Approved :: MIT License
Classifier: Natural Language :: English
Classifier: Programming Language :: Python :: 2
Classifier: Programming Language :: Python :: 2.7
Classifier: Programming Language :: Python :: 3
Classifier: Programming Language :: Python :: 3.4
Classifier: Programming Language :: Python :: 3.5
Classifier: Programming Language :: Python :: 3.6
Requires-Dist: django-simplemde (==0.1.2)
Requires-Dist: dj-markdown (==0.1.2)
Requires-Dist: Pillow (==5.4.1)
Requires-Dist: django
